geotifffile/__init__.py
geotifffile/geotifffile.py
geotifffile-0.1.0.dist-info/METADATA
geotifffile-0.1.0.dist-info/WHEEL
geotifffile-0.1.0.dist-info/licenses/LICENSE
geotifffile-0.1.0.dist-info/RECORD
