Metadata-Version: 2.4
Name: geotifffile
Version: 0.1.0
Summary: Read geotiffs into xarray
Project-URL: Homepage, https://github.com/MutaharChalmers/geotifffile
Author-email: Mutahar Chalmers <mutahar.chalmers@gmail.com>
License: MIT License
License-File: LICENSE
Classifier: Development Status :: 4 - Beta
Classifier: Intended Audience :: Science/Research
Classifier: License :: OSI Approved :: MIT License
Classifier: Operating System :: OS Independent
Classifier: Programming Language :: Python :: 3
Classifier: Topic :: Scientific/Engineering
Requires-Python: >=3.11
Requires-Dist: s3fs
Requires-Dist: tifffile
